{"id":1188138198351990797,"date":"Sat Oct 26 16:59:55 +0000 2019","text":"RT @APompliano: This week in crypto:\n\n1. China going all in on blockchain\n2. Bitcoin up 30%+ in one day\n3. Bakkt hits volume all-time highs…","user":"bradpierced3","favorite_count":0,"retweet_count":0,"followers_count":1322}
{"id":1188138197508714497,"date":"Sat Oct 26 16:59:55 +0000 2019","text":"RT @saifedean: In the months Facebook spent begging governments to let it replace their central banks, they could have just quietly added b…","user":"CryptoBoof","favorite_count":0,"retweet_count":0,"followers_count":900}
{"id":1188138191892516864,"date":"Sat Oct 26 16:59:54 +0000 2019","text":"📉 Biggest Losers (1 hr) 📉\nV Systems $VSYS -7.98% ❄️\nBytom $BTM -2.75% ❄️\nBitcoin Cash $BCH -2.42% ❄️\nChainlink… https://t.co/f8GzKD42X8","user":"CryptoStatsBot","favorite_count":0,"retweet_count":0,"followers_count":5455}
{"id":1188138191251001349,"date":"Sat Oct 26 16:59:53 +0000 2019","text":"RT @crypto_rand: JUST IN: China's Congress passed a cryptography law on Saturday that could further the country's ramped-up blockchain ambi…","user":"mikiZ51","favorite_count":0,"retweet_count":0,"followers_count":168}
{"id":1188138190902845440,"date":"Sat Oct 26 16:59:53 +0000 2019","text":"@MzwaneleManyi I wrote about this because, this was how I saw posts that inspired me to invest in bitcoin and made… https://t.co/UMRprT5i5u","user":"dthandov","favorite_count":0,"retweet_count":0,"followers_count":467}
{"id":1188138188348502016,"date":"Sat Oct 26 16:59:53 +0000 2019","text":"(Bitcoin Still in a “Local Bear Structure, Inside a Macro Bull Market” – Prominent Analyst)\nhttps://t.co/d8BbeVZsRl… https://t.co/BnQR0XD10f","user":"thecryptorep","favorite_count":0,"retweet_count":0,"followers_count":3951}
{"id":1188138184745467904,"date":"Sat Oct 26 16:59:52 +0000 2019","text":"@RawBTC @Rhythmtrader @jack 4/ I understand the ease of transfer and advantages of borderlessness. But even with th… https://t.co/x178DE2z5r","user":"robhon_","favorite_count":1,"retweet_count":0,"followers_count":488}
{"id":1188138183072141312,"date":"Sat Oct 26 16:59:52 +0000 2019","text":"RT @pierre_rochard: @NoelleInMadrid @coindesk @wsfoxley \"blockchain not bitcoin\" is for totalitarian communists.\n\n\"bitcoin not blockchain\"…","user":"evankaloudis","favorite_count":0,"retweet_count":0,"followers_count":1964}
{"id":1188138180064763904,"date":"Sat Oct 26 16:59:51 +0000 2019","text":"@bond007_crypto @digitalassetbuy @XrpMr @SgtObiWan @AlexCobb_ Elvis was spotted buying Bitcoin","user":"Dimitrykleijer","favorite_count":3,"retweet_count":0,"followers_count":765}
{"id":1188138178105892864,"date":"Sat Oct 26 16:59:50 +0000 2019","text":"RT @NickReichert: Recession Checklist\nhttps://t.co/3g2E5icMDd\n#recession #investing #economy #bitcoin #finance #money #economicslowdown #en…","user":"NickReichert","favorite_count":0,"retweet_count":0,"followers_count":16140}
{"id":1188138177040654336,"date":"Sat Oct 26 16:59:50 +0000 2019","text":"RT @jackcoleman219: RT @ravikikan: Types Of #Blockchain \n\n#infographic #robotics #cryptocurrency #CyberSecurity #Bitcoin #Infographics #sta…","user":"WamaithaNyamu","favorite_count":0,"retweet_count":0,"followers_count":231}
{"id":1188138162532556803,"date":"Sat Oct 26 16:59:47 +0000 2019","text":"RT @j_howe4: Me and the boys on this glorious Bitcoin Friday @MartyBent @matt_odell @american_hodl @APompliano @MarkYusko https://t.co/ypfb…","user":"KaoBolt","favorite_count":0,"retweet_count":0,"followers_count":82}
{"id":1188138158493290496,"date":"Sat Oct 26 16:59:46 +0000 2019","text":"RT @InEarth72: @VincentCrypt46 Guessing.   ➡️China  ➡️C_A  ➡️NWO ♻️ Dark money.\nBitcoin mining with 17S+","user":"Christy43250353","favorite_count":0,"retweet_count":0,"followers_count":4074}
{"id":1188138154076692482,"date":"Sat Oct 26 16:59:45 +0000 2019","text":"One Day You Will Get.\nDo Hard Work In Right Direction.\n#Dreams\n#BlockBusterBigilDiwali \n#bitcoin #Diwali… https://t.co/1dOwKAZJ6c","user":"DreamWorldLife1","favorite_count":2,"retweet_count":0,"followers_count":4}
{"id":1188138150939582467,"date":"Sat Oct 26 16:59:44 +0000 2019","text":"RT @AshBonga: A lesson in VOLATILITY for the 'Bitcoin Is Dying'  brigade. https://t.co/ISxQpT33aI","user":"Bizznerd1","favorite_count":0,"retweet_count":0,"followers_count":215}
{"id":1188138150255824896,"date":"Sat Oct 26 16:59:44 +0000 2019","text":"RT @herrlayusmen: Interesting interview with CEO of @Xago_io @Jurgen_Kuhnel\n\n‘We love Bitcoin, But XRP Solves our Problems’ –Xago CEO\n\n@bon…","user":"SwissbergZug","favorite_count":0,"retweet_count":0,"followers_count":281}
{"id":1188138144488706049,"date":"Sat Oct 26 16:59:42 +0000 2019","text":"@ewnupdates I wrote about this because, this was how I saw posts that inspired me to invest in bitcoin and made pro… https://t.co/Ouzhm231iy","user":"dthandov","favorite_count":0,"retweet_count":0,"followers_count":467}
{"id":1188138139417628672,"date":"Sat Oct 26 16:59:41 +0000 2019","text":"RT @PickACrypto: Don't beat yourself up about the past 24hrs on $BTC.\n\nAbsolutely nobody would have predicted such an enormous pump, even t…","user":"LongVan68882694","favorite_count":0,"retweet_count":0,"followers_count":150}
{"id":1188138138620891136,"date":"Sat Oct 26 16:59:41 +0000 2019","text":"China Passes First-Ever ‘Crypto Law’ Going Into Effect January 2020 #bitcoin","user":"nowonbitcoin","favorite_count":0,"retweet_count":0,"followers_count":2055}
{"id":1188138130295185408,"date":"Sat Oct 26 16:59:39 +0000 2019","text":"@ocbtcn @coryklippsten @american_hodl @sthenc @BrainHarrington @Anders_ @Abentley77 That's one reason why @ocbtcn i… https://t.co/18QWtuUTcw","user":"Ragnarly","favorite_count":6,"retweet_count":0,"followers_count":16209}
{"id":1188138128239976450,"date":"Sat Oct 26 16:59:38 +0000 2019","text":"BREAK YOUR KNECK❓❓👀\n#ExWangu #OnlyTachaCan #ENGvsNZ #SaturdayThoughts #SaturdayMotivation #Diwali #UhuruKenyatta… https://t.co/qIiK1RtxXg","user":"Steper637","favorite_count":5,"retweet_count":0,"followers_count":14}
{"id":1188138115275333632,"date":"Sat Oct 26 16:59:35 +0000 2019","text":"@couttsdev HamnettPhillip you just received 100 sats from @couttsdev. You have 7 days to grab them, link Twitter to… https://t.co/Fhuh9KAxJK","user":"bottlepay","favorite_count":1,"retweet_count":0,"followers_count":2575}
{"id":1188138115166298113,"date":"Sat Oct 26 16:59:35 +0000 2019","text":"@collins_belton @Cryptokerenth @spencernoon Can replace ethereum for bitcoin in there, almost the same thing on this occasion.","user":"krugermacro","favorite_count":1,"retweet_count":0,"followers_count":45351}
{"id":1188138111777361921,"date":"Sat Oct 26 16:59:35 +0000 2019","text":"RT @trylolli: 𝐁𝐈𝐓𝐂𝐎𝐈𝐍 𝐈𝐒 𝐎𝐕𝐄𝐑 $𝟗𝐤!\n\nSpreading the joy and celebrating by giving $100 in bitcoin to someone random who likes and RTs this in…","user":"JillyBe27752072","favorite_count":0,"retweet_count":0,"followers_count":84}
{"id":1188138110724530176,"date":"Sat Oct 26 16:59:34 +0000 2019","text":"@Santiag78758327 @DTAPCAP @___Lucky_Luc___ @realDonaldTrump 😂😂\n\nBitcoin = Internet \n\nAOL was a product of the Internet.","user":"JohnBitcoin4","favorite_count":0,"retweet_count":0,"followers_count":180}
{"id":1188138110460149763,"date":"Sat Oct 26 16:59:34 +0000 2019","text":"RT @Douglas_Horn: How do we tell them about Telos? It could top the chart. @HelloTelos\n\nhttps://t.co/qzbYghMhcI","user":"GoodBlockio","favorite_count":0,"retweet_count":0,"followers_count":909}
{"id":1188138110133194752,"date":"Sat Oct 26 16:59:34 +0000 2019","text":"RT @CryptoTownEU: 🚀 Airdrop : Botz Token\n💰 Value : $ 6 + $ 2\n💸 600 + 200 BZT\n🛡 Bot ETH\n⏰ 3 minutes\n\n1. Talk with the Telegram bot: https://…","user":"AlexB92637540","favorite_count":0,"retweet_count":0,"followers_count":2}
{"id":1188138108241530882,"date":"Sat Oct 26 16:59:34 +0000 2019","text":"As Crack Right soon to to be known as the right crack in prison tries to destroy Bitcoin from within it still moves… https://t.co/S1tvz4bhqk","user":"TeamSatoshi","favorite_count":2,"retweet_count":0,"followers_count":542}
{"id":1188138108224770049,"date":"Sat Oct 26 16:59:34 +0000 2019","text":"https://t.co/GCLY4eRP05 PayPal is a hoe ass piece of shit. https://t.co/WRCqQPEj9M #btc #bitcoin","user":"bitcoinmate","favorite_count":0,"retweet_count":0,"followers_count":3155}
{"id":1188138104005316608,"date":"Sat Oct 26 16:59:33 +0000 2019","text":"RT @BintiSports: The Athletics Integrity Unit (AIU) has fingered African Youth Games 800m silver medalist Angela Munguti (18y) 👇\n#10over10…","user":"COkwiri","favorite_count":0,"retweet_count":0,"followers_count":1309}
{"id":1188138100322721793,"date":"Sat Oct 26 16:59:32 +0000 2019","text":"@guardian I wrote about this because, this was how I saw posts that inspired me to invest in bitcoin and made profi… https://t.co/UOX2lftXC7","user":"dthandov","favorite_count":0,"retweet_count":0,"followers_count":467}
{"id":1188138087701811200,"date":"Sat Oct 26 16:59:29 +0000 2019","text":"RT @johnkim77: Bitcoin + Litecoin = Explosion (2) https://t.co/ZsBzkae3SJ","user":"ChriseeeChris","favorite_count":0,"retweet_count":0,"followers_count":46}
{"id":1188138086175301632,"date":"Sat Oct 26 16:59:28 +0000 2019","text":"Recession: Not If, When - Heres How to Prepare Your Investment Portfolio #bitcoin #daveramsey… https://t.co/IS3FEqiKht","user":"bitcoinagile","favorite_count":0,"retweet_count":0,"followers_count":51999}
{"id":1188138083100708864,"date":"Sat Oct 26 16:59:28 +0000 2019","text":"RT @saifedean: In the months Facebook spent begging governments to let it replace their central banks, they could have just quietly added b…","user":"NickSzabo4","favorite_count":0,"retweet_count":0,"followers_count":243174}
{"id":1188138073412030464,"date":"Sat Oct 26 16:59:25 +0000 2019","text":"RT @ChicoCrypto: Going Live At 10:15 AM PST/ 1:15 PM EST\n\n16k Bitcoin Still In Play??\n\n@Snowden Is Prophet Anon of 4chan?\n\nHOLD UP??\n\nCrypt…","user":"GregorMichaj","favorite_count":0,"retweet_count":0,"followers_count":93}
{"id":1188138072338239490,"date":"Sat Oct 26 16:59:25 +0000 2019","text":"RT @APompliano: This week in crypto:\n\n1. China going all in on blockchain\n2. Bitcoin up 30%+ in one day\n3. Bakkt hits volume all-time highs…","user":"GameStorm89","favorite_count":0,"retweet_count":0,"followers_count":871}
{"id":1188138070022987776,"date":"Sat Oct 26 16:59:25 +0000 2019","text":"RT @AshBonga: A lesson in VOLATILITY for the 'Bitcoin Is Dying'  brigade. https://t.co/ISxQpT33aI","user":"KaoBolt","favorite_count":0,"retweet_count":0,"followers_count":82}
{"id":1188138064973127680,"date":"Sat Oct 26 16:59:23 +0000 2019","text":"RT @VincentCrypt46: Ill be more specific on this one.\nWho started Bitcoin? (Good Luck)\nWhat does the company Bitmain do?\nWhere?\nWho started…","user":"Beckycl65261442","favorite_count":0,"retweet_count":0,"followers_count":5594}
{"id":1188138059155398656,"date":"Sat Oct 26 16:59:22 +0000 2019","text":"@Obvi_GlowBabe @MichellePhan Double points for talking down to someone kind who was actually helping people have aw… https://t.co/496HMuQ7Im","user":"1tiffanyyumi","favorite_count":18,"retweet_count":0,"followers_count":2}
{"id":1188138058845216768,"date":"Sat Oct 26 16:59:22 +0000 2019","text":"Recession: Not If, When - Here's How to Prepare Your Investment Portfolio\n\nlink: https://t.co/pNAfGtgrL7\n\n#bitcoin… https://t.co/ZeR9FlC5hW","user":"EngineeringTra3","favorite_count":1,"retweet_count":0,"followers_count":33}
{"id":1188138047164047360,"date":"Sat Oct 26 16:59:19 +0000 2019","text":"There are things you can't describe with words, just live the Bitcoin genesis!!!! https://t.co/OEXTkIuGzi","user":"RamonQuesadaT","favorite_count":0,"retweet_count":1,"followers_count":3532}
{"id":1188138044341342214,"date":"Sat Oct 26 16:59:18 +0000 2019","text":"RT @KelvinOssai: I thought I've seen it all... \nGuys come check this out\n😂😂😂😂😂😂😂😂\n#SpeakYourselfTourFinal #bitcoin https://t.co/xOOcnL0g5p","user":"gigoGHOST","favorite_count":0,"retweet_count":0,"followers_count":3974}
{"id":1188138033046003715,"date":"Sat Oct 26 16:59:16 +0000 2019","text":"RT @eternalcrypto1: #Ledger Nano X 9K follower Giveaway!!!\n\nTo enter simply,\n\n✅ FOLLOW @eternalcrypto1\n\n☑️ LIKE this post\n\n🔁 RETWEET this p…","user":"lordpeynirii","favorite_count":0,"retweet_count":0,"followers_count":588}
{"id":1188138024527450119,"date":"Sat Oct 26 16:59:14 +0000 2019","text":"China lacks the proper philosophy to adopt #cryptocurrency, they will adopt or create only the most centralized and… https://t.co/O74kQH2FSM","user":"This_is_not_tea","favorite_count":6,"retweet_count":1,"followers_count":3448}
{"id":1188138019716521992,"date":"Sat Oct 26 16:59:13 +0000 2019","text":"Bitcoin Is Booming - Here Are 3 Reasons Why Ripple (XRP) Is Not\n\nlink: https://t.co/mpf7ieXtWh\n\n#bitcoin $BTC #BTC… https://t.co/1MUCW82qVV","user":"EngineeringTra3","favorite_count":1,"retweet_count":0,"followers_count":33}
{"id":1188138015874523136,"date":"Sat Oct 26 16:59:12 +0000 2019","text":"RT @Rhythmtrader: We're finally seeing a price correction in bitcoin. Its correct price is $1,000,000.","user":"Vlm4life","favorite_count":0,"retweet_count":0,"followers_count":177}
{"id":1188138011835486208,"date":"Sat Oct 26 16:59:11 +0000 2019","text":"@sabotagebeats @USDisworthless Also don’t use @RobinhoodApp for bitcoin or crypto! You can’t off-line your coins. N… https://t.co/qIA3kN3r8a","user":"CryptoAdam2032","favorite_count":4,"retweet_count":0,"followers_count":698}
{"id":1188138011827064832,"date":"Sat Oct 26 16:59:11 +0000 2019","text":"Every node does the calibration independently. The Bitcoin protocol has a formula written into it which says how th… https://t.co/imBCadd5L4","user":"MoneyMasterX","favorite_count":0,"retweet_count":0,"followers_count":46238}
{"id":1188138009587306496,"date":"Sat Oct 26 16:59:10 +0000 2019","text":"RT @DTAPCAP: Xi holds study session on blockchain tech. When will @realDonaldTrump hold our study session? Xi says he wants to be #1 in bit…","user":"cryptosvzla","favorite_count":0,"retweet_count":0,"followers_count":400}
{"id":1188138008006004737,"date":"Sat Oct 26 16:59:10 +0000 2019","text":"RT RedditBTC: Did the guy who claimed to lose 4 BTC on the Lightning Network lie? There is no on-chain evidence of… https://t.co/unVdwEkN5j","user":"CryptoBuyerSell","favorite_count":0,"retweet_count":0,"followers_count":102}
{"id":1188137984878694405,"date":"Sat Oct 26 16:59:04 +0000 2019","text":"RT @RonnieMoas: Seven weeks ... 49 days ... of 'red candles' blown out in one day $BTC #bitcoin up 40% today ... Technical Analysis is bull…","user":"Vlm4life","favorite_count":0,"retweet_count":0,"followers_count":177}
{"id":1188137983368544256,"date":"Sat Oct 26 16:59:04 +0000 2019","text":"@CryptOrca We love authoritarian governments if it means we make more money!!! Even though bitcoin was created beca… https://t.co/97gY0BHf7a","user":"CryptoAugustuss","favorite_count":3,"retweet_count":0,"followers_count":118}
{"id":1188137982424952832,"date":"Sat Oct 26 16:59:04 +0000 2019","text":"@bbelev @coinyeezy @TheCryptoconomy @Bitcoin_Beyond @kurtwuckertjr @ErikVoorhees He was one of the coordinators of delist bsv","user":"dumpweed91","favorite_count":1,"retweet_count":0,"followers_count":61}
{"id":1188137980805955584,"date":"Sat Oct 26 16:59:03 +0000 2019","text":"RT @APompliano: BREAKING: Chinese President Xi Jinping just publicly supported China going all-in on blockchain technology across their eco…","user":"avagades","favorite_count":0,"retweet_count":0,"followers_count":112}
{"id":1188137977228255238,"date":"Sat Oct 26 16:59:02 +0000 2019","text":"Bitcoin and Gold Could Offer Sanctuary From the Next Recession - BeInCrypto https://t.co/BZxYYevLqr","user":"CoinLook","favorite_count":1,"retweet_count":0,"followers_count":7443}
{"id":1188137973910507520,"date":"Sat Oct 26 16:59:02 +0000 2019","text":"RT @APompliano: This week in crypto:\n\n1. China going all in on blockchain\n2. Bitcoin up 30%+ in one day\n3. Bakkt hits volume all-time highs…","user":"crypticBTC","favorite_count":0,"retweet_count":0,"followers_count":147}
{"id":1188137972941705217,"date":"Sat Oct 26 16:59:01 +0000 2019","text":"RT @JWilliamsFstmed: President Xi - \n\n“Blockchain (Bitcoin) is necessary for gaining economic advantage.”\n\nOver whom?\n\nWake up President Tr…","user":"mattbed88","favorite_count":0,"retweet_count":0,"followers_count":164}
{"id":1188137959070920704,"date":"Sat Oct 26 16:58:58 +0000 2019","text":"RT @cryptokanoon: 🔸 2M users\n\n🔸10K BTC have already been bought through @paxful in India.\n\n🔸3K Bitcoin sold weekly.\n\n🔸351 payment options.…","user":"Devsss7","favorite_count":0,"retweet_count":0,"followers_count":999}
{"id":1188137926426873856,"date":"Sat Oct 26 16:58:50 +0000 2019","text":"RT @APompliano: This week in crypto:\n\n1. China going all in on blockchain\n2. Bitcoin up 30%+ in one day\n3. Bakkt hits volume all-time highs…","user":"RationalCLM","favorite_count":0,"retweet_count":0,"followers_count":44}
{"id":1188137925034291200,"date":"Sat Oct 26 16:58:50 +0000 2019","text":"RT @VincentCrypt46: Ill be more specific on this one.\nWho started Bitcoin? (Good Luck)\nWhat does the company Bitmain do?\nWhere?\nWho started…","user":"MelissaZanghi","favorite_count":0,"retweet_count":0,"followers_count":2484}
{"id":1188137922127634432,"date":"Sat Oct 26 16:58:49 +0000 2019","text":"Bitcoin value: $9179.67","user":"BTCSpeculator","favorite_count":0,"retweet_count":0,"followers_count":353}
{"id":1188137918352805888,"date":"Sat Oct 26 16:58:48 +0000 2019","text":"RT @Rhythmtrader: With bitcoin rising $2000 on the day, now is a good time as any to announce a free newsletter i'll be writing starting ne…","user":"barebonesmining","favorite_count":0,"retweet_count":0,"followers_count":30}
{"id":1188137916066865152,"date":"Sat Oct 26 16:58:48 +0000 2019","text":"RT @FGordillo: Bakkt to Launch Options on Bitcoin Futures in December https://t.co/WiuRkiY4Si #bitcoin #blockchain #fintech","user":"AmberTwemlow","favorite_count":0,"retweet_count":0,"followers_count":3959}
{"id":1188137915781660672,"date":"Sat Oct 26 16:58:48 +0000 2019","text":"3 Million Bitcoin in 2 Seconds: Google Quantum Computer - Bitcoinist https://t.co/kazmyBaTzo via @GoogleNews","user":"REALNEWS2100","favorite_count":1,"retweet_count":0,"followers_count":1428}
{"id":1188137912631734277,"date":"Sat Oct 26 16:58:47 +0000 2019","text":"RT @Crypto_Bitlord: If you think you underestimated that bitcoin pump, you just wait for these #altcoin pumps 🚀🚀🚀🚀🚀🚀🚀","user":"cryptoidiotjs","favorite_count":0,"retweet_count":0,"followers_count":63}
{"id":1188137909267812354,"date":"Sat Oct 26 16:58:46 +0000 2019","text":"@Zoinks84951116 @Tbod13 @ChicoCrypto Unlikely but it did only take a couple days for Bitcoin to go from 10000 to 20000 back in the day.","user":"Calicoin28","favorite_count":0,"retweet_count":0,"followers_count":37}
{"id":1188137903974748161,"date":"Sat Oct 26 16:58:45 +0000 2019","text":"RT @eternalcrypto1: #Ledger Nano X 9K follower Giveaway!!!\n\nTo enter simply,\n\n✅ FOLLOW @eternalcrypto1\n\n☑️ LIKE this post\n\n🔁 RETWEET this p…","user":"PrabalTopno","favorite_count":0,"retweet_count":0,"followers_count":55}
{"id":1188137894931763201,"date":"Sat Oct 26 16:58:43 +0000 2019","text":"RT @sunnydecree: Get it? #Bitcoin https://t.co/HBFyJq94LQ","user":"TheCityIsMine7","favorite_count":0,"retweet_count":0,"followers_count":97}
{"id":1188137888598413314,"date":"Sat Oct 26 16:58:41 +0000 2019","text":"💰For Good Karma Donate Bitcoin:💰 1Co1MoHC8cM3cB8afJ9a3Bm6it7sJXZJGF New video by RichieFromBoston: MOON IN 4K… https://t.co/lGQVtRNMm5","user":"atomic811","favorite_count":0,"retweet_count":0,"followers_count":1095}
{"id":1188137880302096386,"date":"Sat Oct 26 16:58:39 +0000 2019","text":"RT @eternalcrypto1: #Ledger Nano X 9K follower Giveaway!!!\n\nTo enter simply,\n\n✅ FOLLOW @eternalcrypto1\n\n☑️ LIKE this post\n\n🔁 RETWEET this p…","user":"AndreDan13","favorite_count":0,"retweet_count":0,"followers_count":147}
{"id":1188137870088900609,"date":"Sat Oct 26 16:58:37 +0000 2019","text":"Bitcoin may move down today, but I sure enjoyed the ride last night. More fun than a roller coaster ride at Six Fla… https://t.co/z8ZEz2C39S","user":"GaryLeland","favorite_count":6,"retweet_count":1,"followers_count":5777}
{"id":1188137862715367425,"date":"Sat Oct 26 16:58:35 +0000 2019","text":"RT @cryptorecruitr: Bitcoin strongly broke up through the $8,900 - $ 9,200 resistance channel we talked about early yesterday\n\nIt is now re…","user":"TheCityIsMine7","favorite_count":0,"retweet_count":0,"followers_count":97}
{"id":1188137860743876608,"date":"Sat Oct 26 16:58:35 +0000 2019","text":"RT @MiguelCuneta: OK, so we all got excited seeing #Bitcoin make a move it hasn't done in a long time, which is a 40% gain within a day. Co…","user":"Me2018c","favorite_count":0,"retweet_count":0,"followers_count":931}
{"id":1188137858680274944,"date":"Sat Oct 26 16:58:34 +0000 2019","text":"RT @BillyBambrough: Forget China—Is This The Real Reason #Bitcoin, #Ethereum, #Litecoin, And #Ripple’s #XRP Bounced? via @ForbesCrypto http…","user":"CryptoKing169","favorite_count":0,"retweet_count":0,"followers_count":182}
{"id":1188137857614921728,"date":"Sat Oct 26 16:58:34 +0000 2019","text":"RT @infinite27TS: 🆕 CLAPS AIRDROP!\n10000 $DOGE\nRULES:\n🔃Retweet\n👏 50x claps in one @ https://t.co/1gYtAOeQlO ⬇️\nhttps://t.co/uVWDPxcFdM\n📝Com…","user":"tri_wijiantoro","favorite_count":0,"retweet_count":0,"followers_count":8}
{"id":1188137852124745728,"date":"Sat Oct 26 16:58:33 +0000 2019","text":"RT @real_vijay: #Bitcoin moving 40% in one day tells you:\n\n1. On a monetary scale Bitcoin is still tiny.\n\n2. The opportunity is still massi…","user":"nimacheeps","favorite_count":0,"retweet_count":0,"followers_count":456}
{"id":1188137848186245120,"date":"Sat Oct 26 16:58:32 +0000 2019","text":"RT @howardlindzon: A $41,000 Spike print in Bitcoin ... insane ... now up $1,700 today. The volatility remains a feature not a bug. https:/…","user":"Mensah_Esq","favorite_count":0,"retweet_count":0,"followers_count":559}
{"id":1188137847481622529,"date":"Sat Oct 26 16:58:32 +0000 2019","text":"@bbelev @coinyeezy @TheCryptoconomy @Bitcoin_Beyond @kurtwuckertjr @ErikVoorhees Are you delusional?","user":"dumpweed91","favorite_count":0,"retweet_count":0,"followers_count":61}
{"id":1188137839172538368,"date":"Sat Oct 26 16:58:30 +0000 2019","text":"RT @CryptoTownEU: 🚀 Airdrop : Super8 Network\n💸 500 + 20 S8\n🛡 Bot wallet   \n⏰ 4 minutes\n\n📖 Step-by-step guide:\n1. Talk with the Telegram bot…","user":"Trung9981","favorite_count":0,"retweet_count":0,"followers_count":51}
{"id":1188137833229410307,"date":"Sat Oct 26 16:58:28 +0000 2019","text":"@BBCWorld I wrote about this because, this was how I saw posts that inspired me to invest in bitcoin and made profi… https://t.co/A8ZzfOxnQO","user":"priya_davis_","favorite_count":0,"retweet_count":0,"followers_count":13}
{"id":1188137816691224577,"date":"Sat Oct 26 16:58:24 +0000 2019","text":"RT @CCNMarkets: Bitcoin Is Booming – Here Are 3 Reasons Why Ripple (XRP) Is Not https://t.co/Jos2VEDtrK","user":"mikkyvenza","favorite_count":0,"retweet_count":0,"followers_count":131}
{"id":1188137811175714826,"date":"Sat Oct 26 16:58:23 +0000 2019","text":"RT @eternalcrypto1: #Ledger Nano X 9K follower Giveaway!!!\n\nTo enter simply,\n\n✅ FOLLOW @eternalcrypto1\n\n☑️ LIKE this post\n\n🔁 RETWEET this p…","user":"ChivelFitc","favorite_count":0,"retweet_count":0,"followers_count":1038}
{"id":1188137805303685123,"date":"Sat Oct 26 16:58:21 +0000 2019","text":"@JBTheCryptoKing I’m sticking to BTC regardless of how it rises or fall.. was here at 3k, 20k and will still be here... long live bitcoin","user":"AnthonyMelnik","favorite_count":1,"retweet_count":0,"followers_count":213}
{"id":1188137802992631809,"date":"Sat Oct 26 16:58:21 +0000 2019","text":"RT @NischalShetty: BTC is just like a startup. \n\nOne day you feel like the world is ending. \n\nNext day you feel like you're the king of the…","user":"LaliBull","favorite_count":0,"retweet_count":0,"followers_count":2382}
{"id":1188137777541443585,"date":"Sat Oct 26 16:58:15 +0000 2019","text":"Going Live At 10:15 AM PST/ 1:15 PM EST\n\n16k Bitcoin Still In Play??\n\n@Snowden Is Prophet Anon of 4chan?\n\nHOLD UP??… https://t.co/Ba5BjCLBAV","user":"ChicoCrypto","favorite_count":43,"retweet_count":7,"followers_count":15450}
{"id":1188137769056362496,"date":"Sat Oct 26 16:58:13 +0000 2019","text":"RT @fundstrat: +12% rally in #Bitcoin coinciding with strong equity day as S&amp;P 500 nearing all-time highs... \n\n- a reminder of the 'unpopul…","user":"nexs2016","favorite_count":0,"retweet_count":0,"followers_count":776}
{"id":1188137766875328512,"date":"Sat Oct 26 16:58:12 +0000 2019","text":"RT @RonnieMoas: It took three weeks ... December 2017 ... for $BTC #bitcoin to go from $10,000 to $20,000. Would be nice to see history rep…","user":"Me2018c","favorite_count":0,"retweet_count":0,"followers_count":931}
{"id":1188137763360706560,"date":"Sat Oct 26 16:58:11 +0000 2019","text":"RT @Cointelegraph: According to new data, Bitcoin has transferred $11 trillion in wealth since 2009. https://t.co/j3wOM2qgOX","user":"Vismut_Platina_","favorite_count":0,"retweet_count":0,"followers_count":302}
{"id":1188137756209250304,"date":"Sat Oct 26 16:58:10 +0000 2019","text":"RT @leelee19721: @VincentCrypt46 Bitcoin Was Created and Is Run by the NSA\nOne of the main theories about bitcoin is that it is a secret op…","user":"Christy43250353","favorite_count":0,"retweet_count":0,"followers_count":4074}
{"id":1188137753294376960,"date":"Sat Oct 26 16:58:09 +0000 2019","text":"$BTC #bitcoin\nBinance matching server is not performant as it was claimed or bug occured ?\n\nWho can explain this mo… https://t.co/54x5jANmbI","user":"CryptoFan_","favorite_count":4,"retweet_count":2,"followers_count":36}
{"id":1188137750580678657,"date":"Sat Oct 26 16:58:08 +0000 2019","text":"RT @jaimexbt: Welcome to the genesis \n\n#markets #bitcoin #usdt #buy #sell https://t.co/6Bz4mI7pBi","user":"RamonQuesadaT","favorite_count":0,"retweet_count":0,"followers_count":3532}
{"id":1188137747627859970,"date":"Sat Oct 26 16:58:08 +0000 2019","text":"@collins_belton @Cryptokerenth @spencernoon China doesn't do that, odds are close to zero it will.\n\nThis the sequen… https://t.co/vl4nVbpS3I","user":"krugermacro","favorite_count":2,"retweet_count":0,"followers_count":45351}
{"id":1188137746247884800,"date":"Sat Oct 26 16:58:07 +0000 2019","text":"Don't smother each other. No one can grow in the shade.\nDo you Miss and want your ex back?\nHere are sneaky psycholo… https://t.co/V35BwL2eu7","user":"Jhybow","favorite_count":1,"retweet_count":0,"followers_count":507}
{"id":1188137746247884800,"date":"Sat Oct 26 16:58:07 +0000 2019","text":"Don't smother each other. No one can grow in the shade.\nDo you Miss and want your ex back?\nHere are sneaky psycholo… https://t.co/V35BwL2eu7","user":"Jhybow","favorite_count":1,"retweet_count":0,"followers_count":507}
{"id":1188137744565817344,"date":"Sat Oct 26 16:58:07 +0000 2019","text":"RT @bitcoinization: This is just another “blockchain not bitcoin” scam move. Just ignore shitcoiners like @cz_binance who would greatly ben…","user":"TokenHash","favorite_count":0,"retweet_count":0,"followers_count":12917}
{"id":1188137740967272448,"date":"Sat Oct 26 16:58:06 +0000 2019","text":"New Tumblr post: \"China’s Congress Passes Cryptography Law, Effective Jan. 1, 2020\" https://t.co/JuHv1fjPq0 eos, bi… https://t.co/FNJd6MbJU6","user":"bitsites","favorite_count":1,"retweet_count":0,"followers_count":384}
{"id":1188137734335913984,"date":"Sat Oct 26 16:58:05 +0000 2019","text":"Resolute Mining’s sulphide roaster at Syama Gold Mine to be operational in six weeks’ time #Bitcoin #Btc… https://t.co/CSZ9jchr4Z","user":"StartBitcoinOK","favorite_count":0,"retweet_count":0,"followers_count":621}
{"id":1188137718133542912,"date":"Sat Oct 26 16:58:01 +0000 2019","text":"RT @BitBitCrypto: - bitcoin rise from 7,400 to 10,600 in 40sec video\n\nOver $3,000 in less than 24hrs - $BTC https://t.co/seqS0O45iQ","user":"bitcoinmesh","favorite_count":0,"retweet_count":0,"followers_count":431}
{"id":1188137709661052928,"date":"Sat Oct 26 16:57:59 +0000 2019","text":"RT @powerlinep: @jack @Bitcoin Lol everyone else wants to build a digital currency... lol European Union, Facebook, Venezuela. Everyone wan…","user":"powerlinep","favorite_count":0,"retweet_count":0,"followers_count":1989}
{"id":1188137707761033217,"date":"Sat Oct 26 16:57:58 +0000 2019","text":"RT @eternalcrypto1: #Ledger Nano X 9K follower Giveaway!!!\n\nTo enter simply,\n\n✅ FOLLOW @eternalcrypto1\n\n☑️ LIKE this post\n\n🔁 RETWEET this p…","user":"eld_roland","favorite_count":0,"retweet_count":0,"followers_count":1251}
{"id":1188137707761033217,"date":"Sat Oct 26 16:57:58 +0000 2019","text":"RT @eternalcrypto1: #Ledger Nano X 9K follower Giveaway!!!\n\nTo enter simply,\n\n✅ FOLLOW @eternalcrypto1\n\n☑️ LIKE this post\n\n🔁 RETWEET this p…","user":"eld_roland","favorite_count":0,"retweet_count":0,"followers_count":1251}
{"id":1188137704808042496,"date":"Sat Oct 26 16:57:58 +0000 2019","text":"RT @Crypto_Bitlord: If you think you underestimated that bitcoin pump, you just wait for these #altcoin pumps 🚀🚀🚀🚀🚀🚀🚀","user":"THIENVANMENH","favorite_count":0,"retweet_count":0,"followers_count":30}
{"id":1188137691206115328,"date":"Sat Oct 26 16:57:54 +0000 2019","text":"@jack @Bitcoin Lol everyone else wants to build a digital currency... lol European Union, Facebook, Venezuela. Ever… https://t.co/zWUNvBA9r8","user":"powerlinep","favorite_count":1,"retweet_count":1,"followers_count":1989}
{"id":1188137681169063937,"date":"Sat Oct 26 16:57:52 +0000 2019","text":"Making money isn't hard in itself. What's hard is to earn it doing something worth devoting one's life to. \nthank y… https://t.co/hktLXgeZL0","user":"Btccollector1","favorite_count":0,"retweet_count":0,"followers_count":36}
{"id":1188137659459227655,"date":"Sat Oct 26 16:57:47 +0000 2019","text":"BotzToken Airdrop is now Live🚀💰🏆\n\nClick on below link to participate into this amazing #Airdrop🎁… https://t.co/z4S0HH42hq","user":"Emy1945","favorite_count":1,"retweet_count":0,"followers_count":353}
{"id":1188137647954259969,"date":"Sat Oct 26 16:57:44 +0000 2019","text":"What Will Move Crypto Into the Institutional Realm? reported by https://t.co/iZBGCKn7tO ---- #Bitcoin #Adoption… https://t.co/C2C97RjMfT","user":"PaulESamson","favorite_count":0,"retweet_count":0,"followers_count":4110}
{"id":1188137615549071360,"date":"Sat Oct 26 16:57:36 +0000 2019","text":"RT @RedditBTC: Did the guy who claimed to lose 4 BTC on the Lightning Network lie? There is no on-chain evidence of penalty spends. https:/…","user":"kampai_san","favorite_count":0,"retweet_count":0,"followers_count":276}
{"id":1188137612135059459,"date":"Sat Oct 26 16:57:35 +0000 2019","text":"RT @XRPcryptowolf: China launches it's first #DLT application after Xi's #Blockchain-#Bitcoin effect\n\nThe #DLT was launched by the People’s…","user":"digifuture1","favorite_count":0,"retweet_count":0,"followers_count":18}
{"id":1188137602823655427,"date":"Sat Oct 26 16:57:33 +0000 2019","text":"@bigtagon @baiIee remember when we used those sanrio email accounts? i just had to check mine for some password rec… https://t.co/2RYwj7GOqQ","user":"friendlygoo","favorite_count":1,"retweet_count":0,"followers_count":88}
{"id":1188137602362302464,"date":"Sat Oct 26 16:57:33 +0000 2019","text":"RT @infinite27TS: 🆕 CLAPS AIRDROP!\n10000 $DOGE\nRULES:\n🔃Retweet\n👏 50x claps in one @ https://t.co/1gYtAOeQlO ⬇️\nhttps://t.co/uVWDPxcFdM\n📝Com…","user":"richard00295204","favorite_count":0,"retweet_count":0,"followers_count":261}
{"id":1188137597098430464,"date":"Sat Oct 26 16:57:32 +0000 2019","text":"@coryklippsten @saifedean @MartyBent @nntaleb I know, that's why I'm trying to get in their heads.  It's like watch… https://t.co/cSIzvBMs0t","user":"PrestonPysh","favorite_count":4,"retweet_count":0,"followers_count":69560}
{"id":1188137579532574720,"date":"Sat Oct 26 16:57:28 +0000 2019","text":"RT @XRPcryptowolf: China launches it's first #DLT application after Xi's #Blockchain-#Bitcoin effect\n\nThe #DLT was launched by the People’s…","user":"Michael66573056","favorite_count":0,"retweet_count":0,"followers_count":1957}
{"id":1188137578828050433,"date":"Sat Oct 26 16:57:27 +0000 2019","text":"RT @real_vijay: #Bitcoin moving 40% in one day tells you:\n\n1. On a monetary scale Bitcoin is still tiny.\n\n2. The opportunity is still massi…","user":"Zacorbett","favorite_count":0,"retweet_count":0,"followers_count":494}
{"id":1188137578098286593,"date":"Sat Oct 26 16:57:27 +0000 2019","text":"Investment plan\n\nInterBit Investment Ltd offers you several investment plans, starting with a minimum investment of… https://t.co/YDCf05bI57","user":"InterbitI","favorite_count":0,"retweet_count":1,"followers_count":0}
{"id":1188137576462475264,"date":"Sat Oct 26 16:57:27 +0000 2019","text":"RT @BitCoin_Invest_: follow everyone that likes and retweets this to gain new followers.⚠️","user":"_omo_jesu","favorite_count":0,"retweet_count":0,"followers_count":8447}
{"id":1188137576298729472,"date":"Sat Oct 26 16:57:27 +0000 2019","text":"@cz_binance \"While China still bans cryptocurrency trading and its national digital currency is yet hatched,..\" \nNo… https://t.co/xAPXj2raMe","user":"Rahul_Partagas","favorite_count":4,"retweet_count":0,"followers_count":53}
{"id":1188137561287380992,"date":"Sat Oct 26 16:57:23 +0000 2019","text":"RT @gaborgurbacs: 3 reasons why #Bitcoin surged today:\n&gt; CME Bitcoin futures expired today (4PM London time, last Friday of the month).\n\n&gt;…","user":"nexs2016","favorite_count":0,"retweet_count":0,"followers_count":776}
{"id":1188137539401502720,"date":"Sat Oct 26 16:57:18 +0000 2019","text":"There’s one tech giant doing crypto right: Square https://t.co/rNPt52iN8X","user":"cryptosuntsu","favorite_count":1,"retweet_count":1,"followers_count":259}
{"id":1188137539384668161,"date":"Sat Oct 26 16:57:18 +0000 2019","text":"RT @APompliano: This week in crypto:\n\n1. China going all in on blockchain\n2. Bitcoin up 30%+ in one day\n3. Bakkt hits volume all-time highs…","user":"Lagom18","favorite_count":0,"retweet_count":0,"followers_count":17}
{"id":1188137527619792896,"date":"Sat Oct 26 16:57:15 +0000 2019","text":"@cz_binance @APompliano We can't trust Zuck and Co. We'll take @jack &amp; @CashApp  all day, every day. They support d… https://t.co/2FPdf8gYWM","user":"AlgoKrypto","favorite_count":1,"retweet_count":0,"followers_count":78}
{"id":1188137527443689472,"date":"Sat Oct 26 16:57:15 +0000 2019","text":"RT @eternalcrypto1: #Ledger Nano X 9K follower Giveaway!!!\n\nTo enter simply,\n\n✅ FOLLOW @eternalcrypto1\n\n☑️ LIKE this post\n\n🔁 RETWEET this p…","user":"TeeleTeel","favorite_count":0,"retweet_count":0,"followers_count":150}
{"id":1188137521806397440,"date":"Sat Oct 26 16:57:14 +0000 2019","text":"RT @eternalcrypto1: #Ledger Nano X 9K follower Giveaway!!!\n\nTo enter simply,\n\n✅ FOLLOW @eternalcrypto1\n\n☑️ LIKE this post\n\n🔁 RETWEET this p…","user":"jonjon11311410","favorite_count":0,"retweet_count":0,"followers_count":858}
{"id":1188137513950547969,"date":"Sat Oct 26 16:57:12 +0000 2019","text":"RT @alistairmilne: I don't always make Bitcoin memes ... but when I do, the price moves ~$3000 https://t.co/bn1AeE0pPT","user":"KaoBolt","favorite_count":0,"retweet_count":0,"followers_count":82}
{"id":1188137509521383426,"date":"Sat Oct 26 16:57:11 +0000 2019","text":"RT @TonyVal76476318: Too many XRP holders are becoming disillusioned with the value of XRP especially as Bitcoin is pumping for no reason a…","user":"TheChangeLinger","favorite_count":0,"retweet_count":0,"followers_count":738}
{"id":1188137507914997762,"date":"Sat Oct 26 16:57:11 +0000 2019","text":"Bakkt Breaks All-Time High Volume as Bitcoin Posts Massive Gains via @beincrypto https://t.co/c3Iif8rN74\n#bitcoin #bakkt #crypto","user":"CryptoDoc13","favorite_count":0,"retweet_count":0,"followers_count":13}
{"id":1188137506690220038,"date":"Sat Oct 26 16:57:10 +0000 2019","text":"RT @JacobCanfield: A new show for @Discovery: \n\n👉 Digital Gold Rush\n\nFollows different mining operations for Bitcoin and what it takes to s…","user":"Darrellclark2_","favorite_count":0,"retweet_count":0,"followers_count":18}
{"id":1188137505641644034,"date":"Sat Oct 26 16:57:10 +0000 2019","text":"RT @MvPrazo: Fintech industry faces challenges and the solution to this is blockchain technology because it powers bitcoin transactions,tha…","user":"terex444","favorite_count":0,"retweet_count":0,"followers_count":11407}
{"id":1188137500843356161,"date":"Sat Oct 26 16:57:09 +0000 2019","text":"#Bitcoin [BTC] and #Crypto Market Volatility Threatens #Altcoin Dominance Again  https://t.co/Ld3pZK7pwJ via [Coin… https://t.co/lmiSqWM0nu","user":"bitcoin_jar","favorite_count":0,"retweet_count":0,"followers_count":27}
{"id":1188137499996180481,"date":"Sat Oct 26 16:57:09 +0000 2019","text":"LOOK what I've received today! 🥳👍 Thanks @DiiiDouble buddy! Now lets use them to promote $via coin!! 🤑 #bitcoin… https://t.co/Oi705SILY5","user":"umodmohs","favorite_count":3,"retweet_count":1,"followers_count":123}
{"id":1188137499652251649,"date":"Sat Oct 26 16:57:09 +0000 2019","text":"RT @eternalcrypto1: #Ledger Nano X 9K follower Giveaway!!!\n\nTo enter simply,\n\n✅ FOLLOW @eternalcrypto1\n\n☑️ LIKE this post\n\n🔁 RETWEET this p…","user":"DMwas8","favorite_count":0,"retweet_count":0,"followers_count":32}
{"id":1188137497005420544,"date":"Sat Oct 26 16:57:08 +0000 2019","text":"@RawBTC @Rhythmtrader @jack 3/ But I also get this whole sense of blind faith in bitcoin as a valid currency. To da… https://t.co/jfCpFuuC9I","user":"robhon_","favorite_count":1,"retweet_count":0,"followers_count":488}
{"id":1188137494010834945,"date":"Sat Oct 26 16:57:07 +0000 2019","text":"RT @22loops: BITCOIN BOTTOM 24 OCT 2019","user":"einsamerjager","favorite_count":0,"retweet_count":0,"followers_count":107}
{"id":1188137492224135169,"date":"Sat Oct 26 16:57:07 +0000 2019","text":"RT @trylolli: 𝐁𝐈𝐓𝐂𝐎𝐈𝐍 𝐈𝐒 𝐎𝐕𝐄𝐑 $𝟗𝐤!\n\nSpreading the joy and celebrating by giving $100 in bitcoin to someone random who likes and RTs this in…","user":"itsdjsuck","favorite_count":0,"retweet_count":0,"followers_count":54}
{"id":1188137488738471938,"date":"Sat Oct 26 16:57:06 +0000 2019","text":"@ClaraJeffery Also, as soon as the opportunity zone provision was passed, every grifter who’d previously been in go… https://t.co/edtea0fPLA","user":"sarharogres","favorite_count":1,"retweet_count":0,"followers_count":354}
{"id":1188137485244780549,"date":"Sat Oct 26 16:57:05 +0000 2019","text":"RT @eternalcrypto1: #Ledger Nano X 9K follower Giveaway!!!\n\nTo enter simply,\n\n✅ FOLLOW @eternalcrypto1\n\n☑️ LIKE this post\n\n🔁 RETWEET this p…","user":"mcelroy_sg","favorite_count":0,"retweet_count":0,"followers_count":45}
{"id":1188137480379338754,"date":"Sat Oct 26 16:57:04 +0000 2019","text":"RT @BitCoin_Invest_: follow everyone that likes and retweets this to gain new followers.⚠️","user":"nongioco","favorite_count":0,"retweet_count":0,"followers_count":5900}
{"id":1188137478739378176,"date":"Sat Oct 26 16:57:04 +0000 2019","text":"RT @SoloRocknroll: it thrills me to see so many people really excited about bitcoin...but it is important to remember what it is all about…","user":"Michael_Laake","favorite_count":0,"retweet_count":0,"followers_count":2116}
{"id":1188137476826771459,"date":"Sat Oct 26 16:57:03 +0000 2019","text":"RT @MannerCookie: Somebody call China and remind them that SatoXi said to buy bitcoin.","user":"joeyfingers2","favorite_count":0,"retweet_count":0,"followers_count":809}
{"id":1188137472988864512,"date":"Sat Oct 26 16:57:02 +0000 2019","text":"@SacchiSadhana @Bitcoin_fish   follow back within 24 hours","user":"Bitcoin_fish","favorite_count":4,"retweet_count":1,"followers_count":456}
{"id":1188137471974019073,"date":"Sat Oct 26 16:57:02 +0000 2019","text":"RT @APompliano: Someone tell President @realDonaldTrump that there are only 21 million Bitcoin and China is planning to buy them all. \n\nThi…","user":"DrsFayat","favorite_count":0,"retweet_count":0,"followers_count":30}
{"id":1188137467007909889,"date":"Sat Oct 26 16:57:01 +0000 2019","text":"$90,000+ Potential\nGet Paid In Bitcoin\n$2 Business \nGet Freedom","user":"WilliamIkiabo9","favorite_count":0,"retweet_count":0,"followers_count":35}
{"id":1188137466118594560,"date":"Sat Oct 26 16:57:01 +0000 2019","text":"RT @Bakkt: Today we set a new daily record of 1,179 Bakkt Bitcoin Futures contracts traded","user":"nexs2016","favorite_count":0,"retweet_count":0,"followers_count":776}
{"id":1188137457130360832,"date":"Sat Oct 26 16:56:58 +0000 2019","text":"@CashSupport bought bitcoin an hour ago and sent it out never received it","user":"DrLogics2","favorite_count":0,"retweet_count":0,"followers_count":7}
{"id":1188137455452672000,"date":"Sat Oct 26 16:56:58 +0000 2019","text":"RT @DTAPCAP: Xi holds study session on blockchain tech. When will @realDonaldTrump hold our study session? Xi says he wants to be #1 in bit…","user":"JohnBitcoin4","favorite_count":0,"retweet_count":0,"followers_count":180}
{"id":1188137450679484416,"date":"Sat Oct 26 16:56:57 +0000 2019","text":"RT @herrlayusmen: Interesting interview with CEO of @Xago_io @Jurgen_Kuhnel\n\n‘We love Bitcoin, But XRP Solves our Problems’ –Xago CEO\n\n@bon…","user":"Dave_Jonez_02","favorite_count":0,"retweet_count":0,"followers_count":8605}
{"id":1188137440420093952,"date":"Sat Oct 26 16:56:54 +0000 2019","text":"Good morning #USA...🇺🇸..🌋\n\nAnalytics: after the collapse #Digitalgold aka #Bitcoin and #Blockchain Technology era w… https://t.co/KBbBF1xSKc","user":"Gusterov_","favorite_count":0,"retweet_count":0,"followers_count":104}
{"id":1188137430723055616,"date":"Sat Oct 26 16:56:52 +0000 2019","text":"RT @BitCoin_Invest_: follow everyone that likes this. 😀","user":"Trendhub9ja","favorite_count":0,"retweet_count":0,"followers_count":4736}
{"id":1188137428420349957,"date":"Sat Oct 26 16:56:52 +0000 2019","text":"RT @american_hodl: Bitcoin is king 👑 \n\nWe just soldiers 💣","user":"blockchainmikey","favorite_count":0,"retweet_count":0,"followers_count":1072}
{"id":1188137422858739717,"date":"Sat Oct 26 16:56:50 +0000 2019","text":"Ethereum Classic (ETC) 0.00049739 BTC (-11.50%), time to buy the ETCBTC dip?\n@altcoingazette… https://t.co/DydwatOC0K","user":"altcoingazette","favorite_count":1,"retweet_count":0,"followers_count":349}
{"id":1188137421977743361,"date":"Sat Oct 26 16:56:50 +0000 2019","text":"RT @real_vijay: #Bitcoin moving 40% in one day tells you:\n\n1. On a monetary scale Bitcoin is still tiny.\n\n2. The opportunity is still massi…","user":"ameryaghi","favorite_count":0,"retweet_count":0,"followers_count":12682}
{"id":1188137412708442112,"date":"Sat Oct 26 16:56:48 +0000 2019","text":"@Blake_Gambino Is bitcoin a good investment for business?","user":"D0peSoles","favorite_count":1,"retweet_count":1,"followers_count":125}
{"id":1188137389107171329,"date":"Sat Oct 26 16:56:42 +0000 2019","text":"RT @johnkim77: Bitcoin + Litecoin = Explosion (2) https://t.co/ZsBzkae3SJ","user":"palmbeachhair","favorite_count":0,"retweet_count":0,"followers_count":11186}
{"id":1188137387903410179,"date":"Sat Oct 26 16:56:42 +0000 2019","text":"RT @rogerkver: Goldman Sachs, last 20 years:\n\n- $9.6+ billion in fines\n- 28 offences\n- Mortgage abuses\n- Securities abuses\n- Trading violat…","user":"trackingcryptos","favorite_count":0,"retweet_count":0,"followers_count":629}
{"id":1188137386124947456,"date":"Sat Oct 26 16:56:42 +0000 2019","text":"RT @GoodVibes_Decor: Shop home decor products at https://t.co/QFrqHICOML &amp; pay with #cryptocurrencies! Finalize orders easily using #Bitcoi…","user":"Trevtron4","favorite_count":0,"retweet_count":0,"followers_count":170}
{"id":1188137384195559424,"date":"Sat Oct 26 16:56:41 +0000 2019","text":"RT @real_vijay: #Bitcoin moving 40% in one day tells you:\n\n1. On a monetary scale Bitcoin is still tiny.\n\n2. The opportunity is still massi…","user":"Mrmerrington","favorite_count":0,"retweet_count":0,"followers_count":96}
{"id":1188137381230235648,"date":"Sat Oct 26 16:56:40 +0000 2019","text":"RT @RelevantPeter: Bitcoin has crashed 10% over the last 12 hours. Could this be the end?!","user":"joeyfingers2","favorite_count":0,"retweet_count":0,"followers_count":809}
{"id":1188137380328464385,"date":"Sat Oct 26 16:56:40 +0000 2019","text":"This is just another “blockchain not bitcoin” scam move. Just ignore shitcoiners like @cz_binance who would greatly… https://t.co/WCBJho8Hax","user":"bitcoinization","favorite_count":6,"retweet_count":1,"followers_count":3182}
{"id":1188137374318059521,"date":"Sat Oct 26 16:56:39 +0000 2019","text":"Free Bitcoin Cash - Apps on Google Play https://t.co/1Uv24yij73","user":"ivan4uk1982","favorite_count":0,"retweet_count":0,"followers_count":1354}
{"id":1188137363114987520,"date":"Sat Oct 26 16:56:36 +0000 2019","text":"RT @KelvinOssai: I thought I've seen it all... \nGuys come check this out\n😂😂😂😂😂😂😂😂\n#SpeakYourselfTourFinal #bitcoin https://t.co/xOOcnL0g5p","user":"TIMEEIII","favorite_count":0,"retweet_count":0,"followers_count":2304}
{"id":1188137359080132609,"date":"Sat Oct 26 16:56:35 +0000 2019","text":"Me: \"bitcoin prices have gone up 41%\"\nBoss: \"do you have any bitcoin\"\nMe: \"no I just think it would be cool if I did\"","user":"b80y3113","favorite_count":3,"retweet_count":0,"followers_count":84}
{"id":1188137351136055296,"date":"Sat Oct 26 16:56:33 +0000 2019","text":"RT @saifedean: Facebook's billion+ users would've immediately given it the biggest bitcoin payments network in the world &amp; a formidable fir…","user":"MattyIceN","favorite_count":0,"retweet_count":0,"followers_count":26}
{"id":1188137349093441536,"date":"Sat Oct 26 16:56:33 +0000 2019","text":"RT @APompliano: This week in crypto:\n\n1. China going all in on blockchain\n2. Bitcoin up 30%+ in one day\n3. Bakkt hits volume all-time highs…","user":"verymanley","favorite_count":0,"retweet_count":0,"followers_count":594}
{"id":1188137329011187712,"date":"Sat Oct 26 16:56:28 +0000 2019","text":"@James79349611 @shhhhhh_o I think it's called a \"general strike\". The problem is that they have everyone so indebte… https://t.co/UUUfeR7sfy","user":"meekers999","favorite_count":0,"retweet_count":0,"followers_count":2100}
{"id":1188137319385255942,"date":"Sat Oct 26 16:56:26 +0000 2019","text":"RT @RampCapitalLLC: Bitcoin down $1400 since I went to sleep last night. Normal.","user":"MattDegenhardt","favorite_count":0,"retweet_count":0,"followers_count":236}
{"id":1188137316839124993,"date":"Sat Oct 26 16:56:25 +0000 2019","text":"RT @Rhythmtrader: With bitcoin rising $2000 on the day, now is a good time as any to announce a free newsletter i'll be writing starting ne…","user":"sledillac","favorite_count":0,"retweet_count":0,"followers_count":115}
{"id":1188137315702411264,"date":"Sat Oct 26 16:56:25 +0000 2019","text":"I'm tired of setting news articles about Bitcoin prices. You might as well be posting reaching forms or Vegas odds.… https://t.co/0WLVGHz1RK","user":"terracnosaur","favorite_count":2,"retweet_count":0,"followers_count":96}
{"id":1188137314851184640,"date":"Sat Oct 26 16:56:25 +0000 2019","text":"RT @nikcantmine: Jack Dorsey said “hell no” to joining the Libra Association\n\n@jack you absolute KING \n\nJack is doing bitcoin right. I love…","user":"macguyvermedia","favorite_count":0,"retweet_count":0,"followers_count":437}
{"id":1188137312913416193,"date":"Sat Oct 26 16:56:24 +0000 2019","text":"RT @APompliano: Someone tell President @realDonaldTrump that there are only 21 million Bitcoin and China is planning to buy them all. \n\nThi…","user":"robbe28","favorite_count":0,"retweet_count":0,"followers_count":826}
{"id":1188137312087105543,"date":"Sat Oct 26 16:56:24 +0000 2019","text":"RT @BitCoin_Invest_: follow everyone that likes this. 😀","user":"Davidleno8","favorite_count":0,"retweet_count":0,"followers_count":11143}
{"id":1188137305204113408,"date":"Sat Oct 26 16:56:22 +0000 2019","text":"RT @APompliano: BREAKING: Chinese President Xi Jinping just publicly supported China going all-in on blockchain technology across their eco…","user":"Mul38807543","favorite_count":0,"retweet_count":0,"followers_count":221}
{"id":1188137303828504576,"date":"Sat Oct 26 16:56:22 +0000 2019","text":"@HaggsBoson @tmccarthyv94 @Rhythmtrader Bitcoin isn't money either. You're selling rarity and transparency. But it'… https://t.co/XhsIz9DKWf","user":"60DayTrading","favorite_count":0,"retweet_count":0,"followers_count":1428}
{"id":1188137297700687873,"date":"Sat Oct 26 16:56:20 +0000 2019","text":"For your Customizable Shirt, Hoodies, Sweatshirts, Crop tops...Or wears with your name, words, pictures branded on… https://t.co/JM7MLxmwjC","user":"hashtagscouture","favorite_count":12,"retweet_count":5,"followers_count":95}
{"id":1188137293024059395,"date":"Sat Oct 26 16:56:19 +0000 2019","text":"RT @APompliano: This week in crypto:\n\n1. China going all in on blockchain\n2. Bitcoin up 30%+ in one day\n3. Bakkt hits volume all-time highs…","user":"blockchainmikey","favorite_count":0,"retweet_count":0,"followers_count":1072}
{"id":1188137284341846017,"date":"Sat Oct 26 16:56:17 +0000 2019","text":"İ like BİTCOİN..\n#YEMEGİNİSEC @ Zeytin Cafe https://t.co/fA3oYla1Mv","user":"mehmetkocal1","favorite_count":0,"retweet_count":0,"followers_count":108}
{"id":1188137284044050432,"date":"Sat Oct 26 16:56:17 +0000 2019","text":"RT @gualestrit: 📌Resumen Semanal\n\nDow          +0.7%\nS&amp;P 500   +1.2%\nNasdaq     +1.9%\nRussell 2k +1.4%\nCBOE VIX -11.2%\n\nEUR/USD -0.81%\nUSD/…","user":"MarcoDaCostaFX","favorite_count":0,"retweet_count":0,"followers_count":3246}
{"id":1188137271142354944,"date":"Sat Oct 26 16:56:14 +0000 2019","text":"RT @SportsbookBTC: NHL - theScore 🏒 Report: Sharks' Dillon won't face discipline for hit on Matthews https://t.co/hJC6seEpMV ►  https://t.c…","user":"rixon_isaac","favorite_count":0,"retweet_count":0,"followers_count":633}
{"id":1188137270458617864,"date":"Sat Oct 26 16:56:14 +0000 2019","text":"Spending Crypto using https://t.co/cyYKXbvwPM https://t.co/HjwCimKSXM via @YouTube @cryptocom\n#bitcoin $MCO #MCOVisaCard","user":"The_CryptoDad","favorite_count":1,"retweet_count":0,"followers_count":639}
{"id":1188137267996454912,"date":"Sat Oct 26 16:56:13 +0000 2019","text":"RT @JuicyFruityyy: first time i have seen bitcoin actually trend!\n\nfor those wondering why bitcoin jumped nearly 30% its because the presid…","user":"mariaa0696","favorite_count":0,"retweet_count":0,"followers_count":708}
{"id":1188137236446887936,"date":"Sat Oct 26 16:56:06 +0000 2019","text":"HT: Karamoh turns Inter around https://t.co/cO55vDgJfo ⟶ via https://t.co/0I4IIflkwI","user":"SportsbookBTC","favorite_count":0,"retweet_count":0,"followers_count":28548}
{"id":1188137232806240256,"date":"Sat Oct 26 16:56:05 +0000 2019","text":"NHL - theScore 🏒 Report: Sharks' Dillon won't face discipline for hit on Matthews https://t.co/hJC6seEpMV ►… https://t.co/c6WxSPPNkQ","user":"SportsbookBTC","favorite_count":1,"retweet_count":1,"followers_count":28548}
{"id":1188137225935937536,"date":"Sat Oct 26 16:56:03 +0000 2019","text":"RT @Bitcoin_org_: @cz_binance @APompliano It's Bitcoin","user":"Bitcoin_org_","favorite_count":0,"retweet_count":0,"followers_count":655}
{"id":1188137216587026432,"date":"Sat Oct 26 16:56:01 +0000 2019","text":"When will people realize that there won't be any more alt season ever.\n\nIt's all about Bitcoin now. Will it gather… https://t.co/qsRVnxdrK2","user":"pepoliopo","favorite_count":17,"retweet_count":1,"followers_count":358}
{"id":1188137207154036736,"date":"Sat Oct 26 16:55:59 +0000 2019","text":"RT @JoshMcGruff: Back in my day China banned bitcoin and ruined our livelihoods.\n\nKids have it so easy these days. https://t.co/ghn6dETytW","user":"mattbed88","favorite_count":0,"retweet_count":0,"followers_count":164}
{"id":1188137206306598912,"date":"Sat Oct 26 16:55:59 +0000 2019","text":"RT @BlockDecentral: great event today, lots of guests and lots of great discussion. Join us next week for even more #crypto fun #bitcoin #e…","user":"meltelbrot","favorite_count":0,"retweet_count":0,"followers_count":889}
{"id":1188137204700176384,"date":"Sat Oct 26 16:55:58 +0000 2019","text":"#HappyDiwali \n#Ayodhya \n#RugbyWorldCup19 \n#SaturdayMotivation \n#market \n#BSE \n#NSE \n#clearsmaetsense \n#slogantagsz… https://t.co/U9WMUbwFFe","user":"slogantagsz","favorite_count":5,"retweet_count":0,"followers_count":16}
{"id":1188137202838048773,"date":"Sat Oct 26 16:55:58 +0000 2019","text":"RT @eternalcrypto1: #Ledger Nano X 9K follower Giveaway!!!\n\nTo enter simply,\n\n✅ FOLLOW @eternalcrypto1\n\n☑️ LIKE this post\n\n🔁 RETWEET this p…","user":"fonzo654","favorite_count":0,"retweet_count":0,"followers_count":304}
{"id":1188137185180049408,"date":"Sat Oct 26 16:55:54 +0000 2019","text":"@emylacapra The intended purpose of Bitcoin users is not to run their own nodes. Slightly better... 1.2 as in now ?","user":"DavidA1337","favorite_count":0,"retweet_count":0,"followers_count":48}
{"id":1188137175046643718,"date":"Sat Oct 26 16:55:51 +0000 2019","text":"RT @amlivemon: You have to be completely oblivious or totally corrupt to justify anything pro bitcoin. You are just feeding this Chinese pu…","user":"BharathQuant","favorite_count":0,"retweet_count":0,"followers_count":339}
{"id":1188137164091133953,"date":"Sat Oct 26 16:55:49 +0000 2019","text":"Bubbles Everywhere...only place to hide is in Bitcoin \n\n@APompliano\n\nANOTHER STOCK MARKET CRASH? Nobel Prize winnin… https://t.co/zDjUmUxSJC","user":"IndyBlockChain","favorite_count":0,"retweet_count":0,"followers_count":152}
{"id":1188137164091133953,"date":"Sat Oct 26 16:55:49 +0000 2019","text":"Bubbles Everywhere...only place to hide is in Bitcoin \n\n@APompliano\n\nANOTHER STOCK MARKET CRASH? Nobel Prize winnin… https://t.co/zDjUmUxSJC","user":"IndyBlockChain","favorite_count":0,"retweet_count":0,"followers_count":152}
{"id":1188137162824470528,"date":"Sat Oct 26 16:55:48 +0000 2019","text":"RT @real_vijay: #Bitcoin moving 40% in one day tells you:\n\n1. On a monetary scale Bitcoin is still tiny.\n\n2. The opportunity is still massi…","user":"Ragnarly","favorite_count":0,"retweet_count":0,"followers_count":16209}
{"id":1188137157174542336,"date":"Sat Oct 26 16:55:47 +0000 2019","text":"If you won the #lottery, how much of your winnings would you invest in #crypto and #bitcoin bitcoin?","user":"b2pLes","favorite_count":0,"retweet_count":0,"followers_count":458}
{"id":1188137155140505600,"date":"Sat Oct 26 16:55:46 +0000 2019","text":"RT @BambouClub: You need to follow @DeribitExchange @skew_markets  @Duganist @MrJozza  and me to get to grips with trading Bitcoin options.…","user":"JBcryptS","favorite_count":0,"retweet_count":0,"followers_count":112}
{"id":1188137150157656064,"date":"Sat Oct 26 16:55:45 +0000 2019","text":"RT @MishaGuttentag: \"While Zuckerberg endured another public humiliation, he demonstrated exactly what not to do . . . Rather than propose…","user":"mattbed88","favorite_count":0,"retweet_count":0,"followers_count":164}
{"id":1188137142960021505,"date":"Sat Oct 26 16:55:44 +0000 2019","text":"RT @CryptoTownEU: 🚀 Airdrop : Botz Token\n💰 Value : $ 6 + $ 2\n💸 600 + 200 BZT\n🛡 Bot ETH\n⏰ 3 minutes\n\n1. Talk with the Telegram bot: https://…","user":"riad_rex","favorite_count":0,"retweet_count":0,"followers_count":4}
{"id":1188137138702966785,"date":"Sat Oct 26 16:55:43 +0000 2019","text":"RT @Bakkt: Today we set a new daily record of 1,179 Bakkt Bitcoin Futures contracts traded","user":"bitcoinchains","favorite_count":0,"retweet_count":0,"followers_count":73}
{"id":1188137133740974080,"date":"Sat Oct 26 16:55:41 +0000 2019","text":"RT @Eljaboom: #bitcoin trading volume evolution by countries. https://t.co/QZlfIPDQcB","user":"Cryptodawnlv","favorite_count":0,"retweet_count":0,"followers_count":93}
{"id":1188137120323588099,"date":"Sat Oct 26 16:55:38 +0000 2019","text":"Bakkt Breaks All-Time High Volume as Bitcoin Posts Massive Gains via @beincrypto https://t.co/uOVX5YOjna","user":"P2PCRYPTOZ","favorite_count":0,"retweet_count":0,"followers_count":741}
{"id":1188137111230308352,"date":"Sat Oct 26 16:55:36 +0000 2019","text":"RT @eternalcrypto1: #Ledger Nano X 9K follower Giveaway!!!\n\nTo enter simply,\n\n✅ FOLLOW @eternalcrypto1\n\n☑️ LIKE this post\n\n🔁 RETWEET this p…","user":"James37021309","favorite_count":0,"retweet_count":0,"followers_count":146}
{"id":1188137111230308352,"date":"Sat Oct 26 16:55:36 +0000 2019","text":"RT @eternalcrypto1: #Ledger Nano X 9K follower Giveaway!!!\n\nTo enter simply,\n\n✅ FOLLOW @eternalcrypto1\n\n☑️ LIKE this post\n\n🔁 RETWEET this p…","user":"James37021309","favorite_count":0,"retweet_count":0,"followers_count":146}
